setup.py
distributions_GBNS/Binomialdistribution.py
distributions_GBNS/Gaussiandistribution.py
distributions_GBNS/Generaldistribution.py
distributions_GBNS/__init__.py
distributions_GBNS.egg-info/PKG-INFO
distributions_GBNS.egg-info/SOURCES.txt
distributions_GBNS.egg-info/dependency_links.txt
distributions_GBNS.egg-info/not-zip-safe
distributions_GBNS.egg-info/top_level.txt