Metadata-Version: 1.0
Name: distributions-GBNS
Version: 0.1
Summary: Gaussian and Binomial distributions
Home-page: UNKNOWN
Author: Chaminie De Silva
Author-email: kaushalyasarathchandra@gmail.com
License: UNKNOWN
Platform: UNKNOWN
